aweson/__init__.py
aweson/core.py
aweson/utilities.py
aweson-3.1.0.dist-info/licenses/LICENSE
aweson-3.1.0.dist-info/METADATA
aweson-3.1.0.dist-info/WHEEL
aweson-3.1.0.dist-info/top_level.txt
aweson-3.1.0.dist-info/RECORD
