Metadata-Version: 2.4
Name: aweson
Version: 3.1.0
Summary: Traversing and manipulating hierarchical info sets (JSON) using pythonic JSON Path-like expressions
Author-email: Ferenc Dosa-Racz <dosarf@gmail.com>
License-Expression: MIT
Project-URL: Homepage, https://github.com/dosarf/aweson
Project-URL: Issues, https://github.com/dosarf/aweson/issues
Project-URL: Changelog, https://github.com/dosarf/aweson/blob/master/CHANGELOG.md
Keywords: JSON,Path,JSON Path,safe navigation
Classifier: Programming Language :: Python :: 3.10
Classifier: Operating System :: OS Independent
Requires-Python: >=3.10
License-File: LICENSE
Provides-Extra: test
Requires-Dist: pytest; extra == "test"
Requires-Dist: pylint; extra == "test"
Requires-Dist: mypy; extra == "test"
Requires-Dist: black; extra == "test"
Requires-Dist: isort; extra == "test"
Provides-Extra: develop
Requires-Dist: build; extra == "develop"
Requires-Dist: twine; extra == "develop"
Dynamic: license-file
